st_discord_nav/__init__.py
st_discord_nav/example.py
st_discord_nav/frontend/build/asset-manifest.json
st_discord_nav/frontend/build/bootstrap.min.css
st_discord_nav/frontend/build/index.html
st_discord_nav/frontend/build/static/js/main.086f1109.js
st_discord_nav/frontend/build/static/js/main.086f1109.js.LICENSE.txt
st_discord_nav/frontend/build/static/js/main.086f1109.js.map
st_discord_nav-2.1.0.dist-info/LICENSE
st_discord_nav-2.1.0.dist-info/METADATA
st_discord_nav-2.1.0.dist-info/WHEEL
st_discord_nav-2.1.0.dist-info/top_level.txt
st_discord_nav-2.1.0.dist-info/RECORD
